task_assembly/__init__.py
task_assembly/__main__.py
task_assembly/cli.py
task_assembly/client.py
task_assembly/example/batch.csv
task_assembly/example/gold.json
task_assembly/example/handlers.py
task_assembly/example/template.html
task_assembly/handlers.py
task_assembly/utils.py
task_assembly-0.1.28.dist-info/entry_points.txt
task_assembly-0.1.28.dist-info/LICENSE
task_assembly-0.1.28.dist-info/METADATA
task_assembly-0.1.28.dist-info/WHEEL
task_assembly-0.1.28.dist-info/RECORD
