Metadata-Version: 2.1
Name: task-assembly
Version: 0.1.28
Summary: SDK and CLI for using the Task Assembly crowdwork service
License: MIT
Author: Dave Schultz
Author-email: dave@daveschultzconsulting.com
Requires-Python: >=3.8,<4.0
Classifier: License :: OSI Approved :: MIT License
Classifier: Programming Language :: Python :: 3
Classifier: Programming Language :: Python :: 3.8
Classifier: Programming Language :: Python :: 3.9
Classifier: Programming Language :: Python :: 3.10
Classifier: Programming Language :: Python :: 3.11
Classifier: Programming Language :: Python :: 3.12
Requires-Dist: api-client (>=1.3.1,<2.0.0)
Requires-Dist: boto3 (>=1.26.0,<2.0.0)
Requires-Dist: larry (>=0.2.12,<0.3.0)
Requires-Dist: pyyaml (>=6.0,<7.0)
Requires-Dist: tabulate (>=0.9.0,<0.10.0)
Requires-Dist: toml (>=0.10.2,<0.11.0)
